Metadata-Version: 2.1
Name: pypackdemo
Version: 0.0.1
Summary: A python package for interractive mapping.
Home-page: https://github.com/yuusuf4real/pypackdemo
Author: Yusuf Ariyibi
Author-email: yuusuf4real@yahoo.com
License: MIT license
Keywords: pypackdemo
Classifier: Intended Audience :: Developers
Classifier: License :: OSI Approved :: MIT License
Classifier: Natural Language :: English
Classifier: Programming Language :: Python :: 3
Classifier: Programming Language :: Python :: 3.8
Classifier: Programming Language :: Python :: 3.9
Classifier: Programming Language :: Python :: 3.10
Classifier: Programming Language :: Python :: 3.11
Requires-Python: >=3.8
License-File: LICENSE
